hotconsole/__init__.py
hotconsole/helpers.py
hotconsole/hotconsole.py
hotconsole-0.5.0.dist-info/METADATA
hotconsole-0.5.0.dist-info/WHEEL
hotconsole-0.5.0.dist-info/licenses/LICENSE.md
hotconsole-0.5.0.dist-info/RECORD
