Metadata-Version: 2.3
Name: hotconsole
Version: 0.5.0
Summary: Provides an easy way to run your scripts by console commands and hotkeys
Project-URL: Homepage, https://github.com/MishaVoyager/hotconsole
Project-URL: Issues, https://github.com/MishaVoyager/hotconsole/issues
Author-email: Michael Noskov <vecheren@gmail.com>
License-File: LICENSE.md
Keywords: commands,console,hotkeys,hotstrings,scripts,terminal
Classifier: License :: OSI Approved :: MIT License
Classifier: Operating System :: Microsoft :: Windows
Classifier: Programming Language :: Python :: 3
Requires-Python: >=3.10
Requires-Dist: ansicon>=1.89.0
Requires-Dist: keyboard>=0.13.5
Requires-Dist: pydantic>=2.5.3
Requires-Dist: pyperclip>=1.8.2
Requires-Dist: pywin32-ctypes>=0.2.2
Requires-Dist: pywin32>=306
Requires-Dist: requests-toolbelt>=1.0.0
Requires-Dist: requests>=2.31.0
